Caparat/__init__.py
Caparat/aparat.py
Caparat/request.py
Caparat/user.py
Caparat/video.py
CaParat-0.0.1.dist-info/LICENSE
CaParat-0.0.1.dist-info/METADATA
CaParat-0.0.1.dist-info/WHEEL
CaParat-0.0.1.dist-info/top_level.txt
CaParat-0.0.1.dist-info/RECORD
